{
  "project_info": {
    "project_number": "945002021353",
    "project_id": "notesapp-74bfd",
    "storage_bucket": "notesapp-74bfd.appspot.com"
  },
  "client": [
    {
      "client_info": {
        "mobilesdk_app_id": "1:945002021353:android:c06a3b56b44878ae620b78",
        "android_client_info": {
          "package_name": "com.rtntemplateproject"
        }
      },
      "oauth_client": [
        {
          "client_id": "945002021353-ghh655015uulfcq9ln2udo8m27qp59tp.apps.googleusercontent.com",
          "client_type": 3
        }
      ],
      "api_key": [
        {
          "current_key": "AIzaSyAfkwqPt5d_F04hwUY2uGN6EjCsdcr1ixI"
        }
      ],
      "services": {
        "appinvite_service": {
          "other_platform_oauth_client": [
            {
              "client_id": "945002021353-ghh655015uulfcq9ln2udo8m27qp59tp.apps.googleusercontent.com",
              "client_type": 3
            },
            {
              "client_id": "945002021353-nrcdreb8qnvcgflp1bj2bhqr9t2sqmn7.apps.googleusercontent.com",
              "client_type": 2,
              "ios_info": {
                "bundle_id": "org.reactjs.native.example.RTNTemplateProject"
              }
            }
          ]
        }
      }
    }
  ],
  "configuration_version": "1"
}